Metadata-Version: 2.1
Name: python-swift-cloud-tools
Version: 0.1.4
Summary: Admin webapp for OpenStack Keystone and OpenStack Swift.
Home-page: https://github.com/globocom/python-swift-cloud-tools
Author: Storm
Author-email: storm@g.globo
License: UNKNOWN
Platform: UNKNOWN
